djag_scheduler/__init__.py
djag_scheduler/admin.py
djag_scheduler/apps.py
djag_scheduler/event_queue.py
djag_scheduler/managers.py
djag_scheduler/scheduler.py
djag_scheduler/tasks.py
djag_scheduler/tests.py
djag_scheduler/forms/__init__.py
djag_scheduler/forms/periodic_task_forms.py
djag_scheduler/forms/user_action_audit_forms.py
djag_scheduler/forms/user_action_forms.py
djag_scheduler/migrations/0001_initial.py
djag_scheduler/migrations/__init__.py
djag_scheduler/models/__init__.py
djag_scheduler/models/crontab_schedule_model.py
djag_scheduler/models/periodic_task_model.py
djag_scheduler/models/task_dependency_model.py
djag_scheduler/models/user_action_audit_model.py
djag_scheduler/models/user_action_model.py
djag_scheduler/templates/user_action/select_action.html
djag_scheduler/templates/widgets/exception_cron_widget.html
djag_scheduler/templates/widgets/json_field_widget.html
djag_scheduler/widgets/__init__.py
djag_scheduler/widgets/json_field_widget.py
djag_scheduler-2.0.1.dist-info/AUTHORS.md
djag_scheduler-2.0.1.dist-info/LICENSE
djag_scheduler-2.0.1.dist-info/METADATA
djag_scheduler-2.0.1.dist-info/WHEEL
djag_scheduler-2.0.1.dist-info/top_level.txt
djag_scheduler-2.0.1.dist-info/RECORD
