Metadata-Version: 2.1
Name: djag-scheduler
Version: 2.0.1
Summary: 'Django database backed celery periodic task scheduler with support for task dependency graph'
Home-page: https://github.com/m0hithreddy/djag-scheduler
Author: Mohith Reddy
Author-email: dev.m0hithreddy@gmail.com
Project-URL: Bug Tracker, https://github.com/m0hithreddy/djag-scheduler/issues
Classifier: Development Status :: 4 - Beta
Classifier: Environment :: Web Environment
Classifier: Framework :: Django
Classifier: License :: OSI Approved :: MIT License
Classifier: Operating System :: OS Independent
Classifier: Programming Language :: Python
Classifier: Programming Language :: Python :: 3
Classifier: Programming Language :: Python :: 3 :: Only
Classifier: Programming Language :: Python :: 3.6
Classifier: Programming Language :: Python :: 3.7
Classifier: Programming Language :: Python :: 3.8
Classifier: Programming Language :: Python :: 3.9
Classifier: Programming Language :: Python :: 3.10
Classifier: Topic :: Software Development
License-File: LICENSE
License-File: AUTHORS.md
Requires-Dist: Django (<5.0.0,>=4.0.0)
Requires-Dist: celery (<6.0.0,>=5.0.0)
Requires-Dist: croniter (<2.0.0,>=1.0.0)
Requires-Dist: django-timezone-field (<6.0.0,>=5.0.0)
Requires-Dist: toposort (<2.0.0,>=1.0.0)
Requires-Dist: django-json-widget (<2.0.0,>=1.0.0)
Requires-Dist: tzdata (<2023.0,>=2022.1)
